accelbyte_py_sdk/api/sessionbrowser/__init__.py
accelbyte_py_sdk/api/sessionbrowser/errors.py
accelbyte_py_sdk/api/sessionbrowser/models/__init__.py
accelbyte_py_sdk/api/sessionbrowser/models/models_active_custom_game_response.py
accelbyte_py_sdk/api/sessionbrowser/models/models_active_matchmaking_game_response.py
accelbyte_py_sdk/api/sessionbrowser/models/models_add_player_request.py
accelbyte_py_sdk/api/sessionbrowser/models/models_add_player_response.py
accelbyte_py_sdk/api/sessionbrowser/models/models_admin_session_response.py
accelbyte_py_sdk/api/sessionbrowser/models/models_count_active_session_response.py
accelbyte_py_sdk/api/sessionbrowser/models/models_create_session_request.py
accelbyte_py_sdk/api/sessionbrowser/models/models_custom_game_response.py
accelbyte_py_sdk/api/sessionbrowser/models/models_game_session.py
accelbyte_py_sdk/api/sessionbrowser/models/models_game_session_setting.py
accelbyte_py_sdk/api/sessionbrowser/models/models_get_session_history_detailed_response_item.py
accelbyte_py_sdk/api/sessionbrowser/models/models_get_session_history_search_response_item_v2.py
accelbyte_py_sdk/api/sessionbrowser/models/models_get_session_history_search_response_v2.py
accelbyte_py_sdk/api/sessionbrowser/models/models_join_game_session_request.py
accelbyte_py_sdk/api/sessionbrowser/models/models_match_attributes.py
accelbyte_py_sdk/api/sessionbrowser/models/models_match_making.py
accelbyte_py_sdk/api/sessionbrowser/models/models_matching_ally.py
accelbyte_py_sdk/api/sessionbrowser/models/models_matching_party.py
accelbyte_py_sdk/api/sessionbrowser/models/models_pagination.py
accelbyte_py_sdk/api/sessionbrowser/models/models_paging_cursor.py
accelbyte_py_sdk/api/sessionbrowser/models/models_party_member.py
accelbyte_py_sdk/api/sessionbrowser/models/models_recent_player_history.py
accelbyte_py_sdk/api/sessionbrowser/models/models_recent_player_query_response.py
accelbyte_py_sdk/api/sessionbrowser/models/models_server.py
accelbyte_py_sdk_service_sessionbrowser-0.21.0.dist-info/METADATA
accelbyte_py_sdk_service_sessionbrowser-0.21.0.dist-info/WHEEL
accelbyte_py_sdk_service_sessionbrowser-0.21.0.dist-info/top_level.txt
accelbyte_py_sdk_service_sessionbrowser-0.21.0.dist-info/RECORD
