Metadata-Version: 2.4
Name: accelbyte-py-sdk-service-sessionbrowser
Version: 0.21.0
Summary: AccelByte Python SDK - AccelByte Gaming Services Session Browser Service
Requires-Python: >=3.9
Requires-Dist: accelbyte-py-sdk-core
